{  
   "images":{  
      "repositories":[  
         "xoreo/pi-term",
         "<none>",
         "<none>",
         "node",
         "xxmattnappo/cryptpy",
         "<none>",
         "busybox",
         "hello-world",
         "python",
         ""
      ],
      "created":[  
         "11 days ago",
         "5 weeks ago",
         "5 weeks ago",
         "7 weeks ago",
         "6 months ago",
         "6 months ago",
         "7 months ago",
         "7 months ago",
         "8 months ago",
         ""
      ]
   },
   "containers":{  
      "id":[  
         ""
      ],
      "image":[  
         ""
      ],
      "status":[  
         ""
      ]
   }
}